{
  "initializationUrls": [
    "catalog"
  ],
  "parameters": {
    "appName": "Ōtākaro Digital Twin",
    "tabbedCatalog": true,
    "supportEmail": "gri-enquiries+otakaro@canterbury.ac.nz",
    "cesiumIonAccessToken": "$CESIUM_ACCESS_TOKEN",
    "brandBarElements": [
      "<div style=\"display: flex; align-items: center;\">\n  <h1 style=\"color: white;\">Ōtākaro Digital Twin</h1>\n</div>"
    ],
    "brandBarSmallElements": [
      "<div style=\"display: flex; align-items: center;\">\n  <h3 style=\"color: white;\">Ōtākaro Digital Twin</h3>\n</div>"
    ],
    "relatedMaps": []
  }
}
